<?xml version="1.0" encoding="UTF-8" standalone="no"?><sites count="19"><site><county_name>Natrona</county_name><description nil="true"/><feat_class>Populated Place</feat_class><feature_id>36462</feature_id><fips_class>C1</fips_class><fips_county_cd>25</fips_county_cd><full_county_name>Natrona County</full_county_name><link_title nil="true"/><url>http://www.casperwy.gov/</url><name>Casper</name><primary_latitude>42.86</primary_latitude><primary_longitude>-106.31</primary_longitude><state_abbreviation>WY</state_abbreviation><state_name>Wyoming</state_name></site><site><county_name>Laramie</county_name><description nil="true"/><feat_class>Populated Place</feat_class><feature_id>36463</feature_id><fips_class>C1</fips_class><fips_county_cd>21</fips_county_cd><full_county_name>Laramie County</full_county_name><link_title nil="true"/><url>http://www.cheyennecity.org/</url><name>Cheyenne</name><primary_latitude>41.13</primary_latitude><primary_longitude>-104.82</primary_longitude><state_abbreviation>WY</state_abbreviation><state_name>Wyoming</state_name></site><site><county_name>Converse</county_name><description nil="true"/><feat_class>Populated Place</feat_class><feature_id>36473</feature_id><fips_class>C1</fips_class><fips_county_cd>9</fips_county_cd><full_county_name>Converse County</full_county_name><link_title nil="true"/><url>http://www.cityofdouglaswy.com/</url><name>Douglas</name><primary_latitude>42.75</primary_latitude><primary_longitude>-105.38</primary_longitude><state_abbreviation>WY</state_abbreviation><state_name>Wyoming</state_name></site><site><county_name>Uinta</county_name><description nil="true"/><feat_class>Populated Place</feat_class><feature_id>36479</feature_id><fips_class>C1</fips_class><fips_county_cd>41</fips_county_cd><full_county_name>Uinta County</full_county_name><link_title nil="true"/><url>http://www.evanstonwy.org/</url><name>Evanston</name><primary_latitude>41.26</primary_latitude><primary_longitude>-110.96</primary_longitude><state_abbreviation>WY</state_abbreviation><state_name>Wyoming</state_name></site><site><county_name>Campbell</county_name><description nil="true"/><feat_class>Populated Place</feat_class><feature_id>36484</feature_id><fips_class>C1</fips_class><fips_county_cd>5</fips_county_cd><full_county_name>Campbell County</full_county_name><link_title nil="true"/><url>http://www.ci.gillette.wy.us/</url><name>Gillette</name><primary_latitude>44.29</primary_latitude><primary_longitude>-105.5</primary_longitude><state_abbreviation>WY</state_abbreviation><state_name>Wyoming</state_name></site><site><county_name>Sweetwater</county_name><description nil="true"/><feat_class>Populated Place</feat_class><feature_id>36488</feature_id><fips_class>C1</fips_class><fips_county_cd>37</fips_county_cd><full_county_name>Sweetwater County</full_county_name><link_title nil="true"/><url>http://www.cityofgreenriver.org/</url><name>Green River</name><primary_latitude>41.52</primary_latitude><primary_longitude>-109.46</primary_longitude><state_abbreviation>WY</state_abbreviation><state_name>Wyoming</state_name></site><site><county_name>Teton</county_name><description nil="true"/><feat_class>Populated Place</feat_class><feature_id>36495</feature_id><fips_class>C1</fips_class><fips_county_cd>39</fips_county_cd><full_county_name>Teton County</full_county_name><link_title nil="true"/><url>http://www.ci.jackson.wy.us/</url><name>Jackson</name><primary_latitude>43.47</primary_latitude><primary_longitude>-110.76</primary_longitude><state_abbreviation>WY</state_abbreviation><state_name>Wyoming</state_name></site><site><county_name>Lincoln</county_name><description nil="true"/><feat_class>Populated Place</feat_class><feature_id>36497</feature_id><fips_class>C1</fips_class><fips_county_cd>23</fips_county_cd><full_county_name>Lincoln County</full_county_name><link_title nil="true"/><url>http://www.kemmerer.org/</url><name>Kemmerer</name><primary_latitude>41.79</primary_latitude><primary_longitude>-110.53</primary_longitude><state_abbreviation>WY</state_abbreviation><state_name>Wyoming</state_name></site><site><county_name>Albany</county_name><description nil="true"/><feat_class>Populated Place</feat_class><feature_id>36502</feature_id><fips_class>C1</fips_class><fips_county_cd>1</fips_county_cd><full_county_name>Albany County</full_county_name><link_title nil="true"/><url>http://www.ci.laramie.wy.us/</url><name>Laramie</name><primary_latitude>41.31</primary_latitude><primary_longitude>-105.59</primary_longitude><state_abbreviation>WY</state_abbreviation><state_name>Wyoming</state_name></site><site><county_name>Uinta</county_name><description nil="true"/><feat_class>Populated Place</feat_class><feature_id>36507</feature_id><fips_class>C1</fips_class><fips_county_cd>41</fips_county_cd><full_county_name>Uinta County</full_county_name><link_title nil="true"/><url>http://lyman.govoffice.com/</url><name>Lyman</name><primary_latitude>41.32</primary_latitude><primary_longitude>-110.29</primary_longitude><state_abbreviation>WY</state_abbreviation><state_name>Wyoming</state_name></site><site><county_name>Carbon</county_name><description nil="true"/><feat_class>Populated Place</feat_class><feature_id>36525</feature_id><fips_class>C1</fips_class><fips_county_cd>7</fips_county_cd><full_county_name>Carbon County</full_county_name><link_title nil="true"/><url>http://www.rawlins-wyoming.com/</url><name>Rawlins</name><primary_latitude>41.79</primary_latitude><primary_longitude>-107.23</primary_longitude><state_abbreviation>WY</state_abbreviation><state_name>Wyoming</state_name></site><site><county_name>Fremont</county_name><description nil="true"/><feat_class>Populated Place</feat_class><feature_id>36527</feature_id><fips_class>C1</fips_class><fips_county_cd>13</fips_county_cd><full_county_name>Fremont County</full_county_name><link_title nil="true"/><url>http://www.riverton.wyoming.com/</url><name>Riverton</name><primary_latitude>43.02</primary_latitude><primary_longitude>-108.38</primary_longitude><state_abbreviation>WY</state_abbreviation><state_name>Wyoming</state_name></site><site><county_name>Sweetwater</county_name><description nil="true"/><feat_class>Populated Place</feat_class><feature_id>36529</feature_id><fips_class>C1</fips_class><fips_county_cd>37</fips_county_cd><full_county_name>Sweetwater County</full_county_name><link_title nil="true"/><url>http://www.rswy.net/</url><name>Rock Springs</name><primary_latitude>41.58</primary_latitude><primary_longitude>-109.2</primary_longitude><state_abbreviation>WY</state_abbreviation><state_name>Wyoming</state_name></site><site><county_name>Carbon</county_name><description nil="true"/><feat_class>Populated Place</feat_class><feature_id>36531</feature_id><fips_class>C1</fips_class><fips_county_cd>7</fips_county_cd><full_county_name>Carbon County</full_county_name><link_title nil="true"/><url>http://www.saratoga.govoffice2.com/</url><name>Saratoga</name><primary_latitude>41.45</primary_latitude><primary_longitude>-106.8</primary_longitude><state_abbreviation>WY</state_abbreviation><state_name>Wyoming</state_name></site><site><county_name>Sheridan</county_name><description nil="true"/><feat_class>Populated Place</feat_class><feature_id>36532</feature_id><fips_class>C1</fips_class><fips_county_cd>33</fips_county_cd><full_county_name>Sheridan County</full_county_name><link_title nil="true"/><url>http://www.city-sheridan-wy.com/</url><name>Sheridan</name><primary_latitude>44.79</primary_latitude><primary_longitude>-106.95</primary_longitude><state_abbreviation>WY</state_abbreviation><state_name>Wyoming</state_name></site><site><county_name>Lincoln</county_name><description nil="true"/><feat_class>Populated Place</feat_class><feature_id>36538</feature_id><fips_class>C1</fips_class><fips_county_cd>23</fips_county_cd><full_county_name>Lincoln County</full_county_name><link_title nil="true"/><url>http://www.thayne-wy.com/</url><name>Thayne</name><primary_latitude>42.92</primary_latitude><primary_longitude>-111</primary_longitude><state_abbreviation>WY</state_abbreviation><state_name>Wyoming</state_name></site><site><county_name>Goshen</county_name><description nil="true"/><feat_class>Populated Place</feat_class><feature_id>36540</feature_id><fips_class>C1</fips_class><fips_county_cd>15</fips_county_cd><full_county_name>Goshen County</full_county_name><link_title nil="true"/><url>http://www.city-of-torrington.org/</url><name>Torrington</name><primary_latitude>42.06</primary_latitude><primary_longitude>-104.18</primary_longitude><state_abbreviation>WY</state_abbreviation><state_name>Wyoming</state_name></site><site><county_name>Washakie</county_name><description nil="true"/><feat_class>Populated Place</feat_class><feature_id>36545</feature_id><fips_class>C1</fips_class><fips_county_cd>43</fips_county_cd><full_county_name>Washakie County</full_county_name><link_title nil="true"/><url>http://www.cityofworland.org/</url><name>Worland</name><primary_latitude>44.01</primary_latitude><primary_longitude>-107.95</primary_longitude><state_abbreviation>WY</state_abbreviation><state_name>Wyoming</state_name></site><site><county_name>Campbell</county_name><description nil="true"/><feat_class>Populated Place</feat_class><feature_id>36546</feature_id><fips_class>C1</fips_class><fips_county_cd>5</fips_county_cd><full_county_name>Campbell County</full_county_name><link_title nil="true"/><url>http://www.wrightwyoming.com/</url><name>Wright</name><primary_latitude>43.74</primary_latitude><primary_longitude>-105.47</primary_longitude><state_abbreviation>WY</state_abbreviation><state_name>Wyoming</state_name></site></sites>